{
  "紅": null,
  "樓": null,
  "红": null,
  "楼": null,
  "夢": null,
  "梦": null,
  "姑": null,
  "娘": null,
  "疼": null,
  "愛": null,
  "爱": null,
  "去": null,
  "世": null,
  "傷": null,
  "心": null,
  "伤": null,
  "弱": null,
  "外": null,
  "婆": null,
  "接": null,
  "舅": null,
  "當": null,
  "当": null,
  "官": null,
  "和": null,
  "氣": null,
  "气": null,
  "可": null,
  "讀": null,
  "書": null,
  "读": null,
  "书": null,
  "古": null,
  "參": null,
  "加": null,
  "参": null,
  "考": null,
  "試": null,
  "试": null,
  "更": null,
  "使": null,
  "罵": null,
  "骂": null,
  "背": null,
  "讓": null,
  "让": null,
  "厲": null,
  "害": null,
  "厉": null,
  "送": null,
  "給": null,
  "给": null,
  "勸": null,
  "劝": null,
  "場": null,
  "场": null,
  "差": null,
  "新": null,
  "房": null,
  "歡": null,
  "樂": null,
  "欢": null,
  "乐": null,
  "燒": null,
  "烧": null,
  "悄": null,
  "幸": null,
  "福": null,
  "想": null,
  "念": null,
  "離": null,
  "開": null,
  "离": null,
  "开": null,
  "出": null,
  "家": null,
  "尚": null,
  "花": null,
  "園": null,
  "园": null,
  "專": null,
  "专": null,
  "落": null,
  "吹": null,
  "潔": null,
  "淨": null,
  "洁": null,
  "净": null,
  "惜": null,
  "哎": null,
  "小": null,
  "踩": null,
  "有": null,
  "弄": null,
  "髒": null,
  "脏": null,
  "修": null,
  "座": null,
  "墳": null,
  "坟": null,
  "掃": null,
  "扫": null,
  "裝": null,
  "装": null,
  "袋": null,
  "子": null,
  "埋": null,
  "化": null,
  "土": null,
  "高": null,
  "貴": null,
  "贵": null,
  "生": null,
  "命": null,
  "愁": null,
  "挺": null,
  "脾": null,
  "難": null,
  "道": null,
  "难": null,
  "談": null,
  "得": null,
  "來": null,
  "谈": null,
  "来": null,
  "行": null,
  "鍛": null,
  "鍊": null,
  "锻": null,
  "炼": null
}